birdnetlib/__init__.py
birdnetlib/analyzer.py
birdnetlib/analyzer_lite.py
birdnetlib/batch.py
birdnetlib/exceptions.py
birdnetlib/main.py
birdnetlib/species.py
birdnetlib/utils.py
birdnetlib/watcher.py
birdnetlib/wavutils.py
birdnetlib/models/README.md
birdnetlib/models/analyzer/BirdNET_GLOBAL_6K_V2.4_Labels.txt
birdnetlib/models/analyzer/BirdNET_GLOBAL_6K_V2.4_MData_Model_V2_FP16.tflite
birdnetlib/models/analyzer/BirdNET_GLOBAL_6K_V2.4_Model_FP32.tflite
birdnetlib/models/analyzer/LICENSE
birdnetlib/models/analyzer/README.md
birdnetlib-0.18.0.dist-info/METADATA
birdnetlib-0.18.0.dist-info/WHEEL
birdnetlib-0.18.0.dist-info/licenses/LICENSE
birdnetlib-0.18.0.dist-info/RECORD
