Metadata-Version: 2.3
Name: birdnetlib
Version: 0.18.0
Summary: A python api for BirdNET-Lite and BirdNET-Analyzer
Project-URL: Source code, https://github.com/joeweiss/birdnetlib
Project-URL: Issues, https://github.com/joeweiss/birdnetlib/issues
Project-URL: Documentation, https://joeweiss.github.io/birdnetlib/
Author-email: Joe Weiss <joe.weiss@gmail.com>
License: Apache-2.0
Classifier: License :: OSI Approved :: Apache Software License
Classifier: Operating System :: OS Independent
Classifier: Programming Language :: Python :: 3.9
Classifier: Programming Language :: Python :: 3.10
Classifier: Programming Language :: Python :: 3.11
Requires-Python: >=3.9
Requires-Dist: matplotlib>=3.5.3
Requires-Dist: pydub==0.25.1
Requires-Dist: requests>=2.28.1
Requires-Dist: watchdog==2.1.9
